Seasonality/Seasonality.py
Seasonality/__init__.py
seasonality_removal-0.1.data/scripts/runner
version/__init__.py
seasonality_removal-0.1.dist-info/METADATA
seasonality_removal-0.1.dist-info/WHEEL
seasonality_removal-0.1.dist-info/top_level.txt
seasonality_removal-0.1.dist-info/RECORD
